quick_sketches.cp38-win32.pyd
quick_sketches-1.0.0.dist-info/LICENSE
quick_sketches-1.0.0.dist-info/METADATA
quick_sketches-1.0.0.dist-info/WHEEL
quick_sketches-1.0.0.dist-info/top_level.txt
quick_sketches-1.0.0.dist-info/RECORD
