Metadata-Version: 2.1
Name: quick-sketches
Version: 1.0.0
Summary: A Library with Fast Sketching Primitives
Home-page: https://github.com/franklynwang/quick-sketches
Author: Franklyn Wang
Author-email: franklynw2000@gmail.com
License: UNKNOWN
Platform: UNKNOWN
License-File: LICENSE
Requires-Dist: numpy (>=1.16)
Requires-Dist: setuptools (>=42.0.0)
Provides-Extra: test
Requires-Dist: pytest ; extra == 'test'
